python_notion_api/__init__.py
python_notion_api/async_api/__init__.py
python_notion_api/async_api/api.py
python_notion_api/async_api/iterators.py
python_notion_api/async_api/notion_block.py
python_notion_api/async_api/notion_database.py
python_notion_api/async_api/notion_page.py
python_notion_api/async_api/retry_strategy.py
python_notion_api/async_api/tests/test_async_api.py
python_notion_api/async_api/tests/test_async_block.py
python_notion_api/async_api/tests/test_async_database.py
python_notion_api/async_api/tests/test_async_page.py
python_notion_api/async_api/tests/test_properties.py
python_notion_api/async_api/tests/test_query.py
python_notion_api/async_api/utils.py
python_notion_api/models/__init__.py
python_notion_api/models/blocks.py
python_notion_api/models/common.py
python_notion_api/models/configurations.py
python_notion_api/models/fields.py
python_notion_api/models/filters.py
python_notion_api/models/iterators.py
python_notion_api/models/objects.py
python_notion_api/models/paginations.py
python_notion_api/models/properties.py
python_notion_api/models/sorts.py
python_notion_api/models/values.py
python_notion_api/sync_api/__init__.py
python_notion_api/sync_api/api.py
python_notion_api/sync_api/test_sync.py
python_notion_api/utils.py
python_notion_api-1.0.0.dist-info/LICENSE
python_notion_api-1.0.0.dist-info/METADATA
python_notion_api-1.0.0.dist-info/WHEEL
python_notion_api-1.0.0.dist-info/RECORD
