Metadata-Version: 2.3
Name: python-notion-api
Version: 1.0.0
Summary: Python wrapper for the official Notion API
Author: Mihails Delmans
Author-email: mihails.delmans@colorifix.com
Requires-Python: >=3.11,<4.0
Classifier: Programming Language :: Python :: 3
Classifier: Programming Language :: Python :: 3.11
Classifier: Programming Language :: Python :: 3.12
Classifier: Programming Language :: Python :: 3.13
Requires-Dist: aiohttp (>=3.8.5,<4.0.0)
Requires-Dist: aiolimiter (>=1.1.0,<2.0.0)
Requires-Dist: loguru (>=0.7.0,<0.8.0)
Requires-Dist: pydantic (>=2,<3)
Requires-Dist: requests (>=2.28.1,<3.0.0)
Requires-Dist: slugify (>=0.0.1,<0.0.2)
